README.rst
setup.py
cssspriter/__init__.py
cssspriter.egg-info/PKG-INFO
cssspriter.egg-info/SOURCES.txt
cssspriter.egg-info/dependency_links.txt
cssspriter.egg-info/entry_points.txt
cssspriter.egg-info/requires.txt
cssspriter.egg-info/top_level.txt