Metadata-Version: 2.1
Name: cssspriter
Version: 0.2.2
Summary: CSS Sprites generator
Home-page: https://github.com/perrinjerome/cssspriter
Author: Jérome Perrin
License: GPL
Keywords: css sprite
Platform: UNKNOWN
